{
  "week": "Week of Mar 08, 2026",
  "updated": "Mar 08, 2026",
  "teams": [
    {
      "rank": 1,
      "lastRank": 1,
      "team": "Duke",
      "rating": 2.524
    },
    {
      "rank": 2,
      "lastRank": 2,
      "team": "Arizona",
      "rating": 2.479
    },
    {
      "rank": 3,
      "lastRank": 3,
      "team": "Michigan",
      "rating": 2.462
    },
    {
      "rank": 4,
      "lastRank": 4,
      "team": "Florida",
      "rating": 2.304
    },
    {
      "rank": 5,
      "lastRank": 5,
      "team": "Gonzaga",
      "rating": 2.166
    },
    {
      "rank": 6,
      "lastRank": 6,
      "team": "Houston",
      "rating": 2.124
    },
    {
      "rank": 7,
      "lastRank": 7,
      "team": "Purdue",
      "rating": 2.102
    },
    {
      "rank": 8,
      "lastRank": 8,
      "team": "Arkansas",
      "rating": 2.081
    },
    {
      "rank": 9,
      "lastRank": 9,
      "team": "Michigan State",
      "rating": 2.067
    },
    {
      "rank": 10,
      "lastRank": 10,
      "team": "Tennessee",
      "rating": 2.066
    },
    {
      "rank": 11,
      "lastRank": 12,
      "team": "Alabama",
      "rating": 2.027
    },
    {
      "rank": 12,
      "lastRank": 13,
      "team": "Illinois",
      "rating": 1.975
    },
    {
      "rank": 13,
      "lastRank": 14,
      "team": "Iowa State",
      "rating": 1.956
    },
    {
      "rank": 14,
      "lastRank": 15,
      "team": "Vanderbilt",
      "rating": 1.929
    },
    {
      "rank": 15,
      "lastRank": 16,
      "team": "UConn",
      "rating": 1.894
    },
    {
      "rank": 16,
      "lastRank": 17,
      "team": "Kentucky",
      "rating": 1.849
    },
    {
      "rank": 17,
      "lastRank": 18,
      "team": "Louisville",
      "rating": 1.83
    },
    {
      "rank": 18,
      "lastRank": 11,
      "team": "Texas Tech",
      "rating": 1.82
    },
    {
      "rank": 19,
      "lastRank": 19,
      "team": "Auburn",
      "rating": 1.774
    },
    {
      "rank": 20,
      "lastRank": 20,
      "team": "Kansas",
      "rating": 1.72
    },
    {
      "rank": 21,
      "lastRank": 21,
      "team": "Utah State",
      "rating": 1.627
    },
    {
      "rank": 22,
      "lastRank": 22,
      "team": "BYU",
      "rating": 1.623
    },
    {
      "rank": 23,
      "lastRank": 23,
      "team": "UCLA",
      "rating": 1.585
    },
    {
      "rank": 24,
      "lastRank": 24,
      "team": "Nebraska",
      "rating": 1.57
    },
    {
      "rank": 25,
      "lastRank": 25,
      "team": "Texas",
      "rating": 1.546
    },
    {
      "rank": 26,
      "lastRank": 26,
      "team": "Wisconsin",
      "rating": 1.536
    },
    {
      "rank": 27,
      "lastRank": 27,
      "team": "Santa Clara",
      "rating": 1.531
    },
    {
      "rank": 28,
      "lastRank": 28,
      "team": "Iowa",
      "rating": 1.511
    },
    {
      "rank": 29,
      "lastRank": 29,
      "team": "Georgia",
      "rating": 1.508
    },
    {
      "rank": 30,
      "lastRank": 30,
      "team": "St. John's",
      "rating": 1.497
    },
    {
      "rank": 31,
      "lastRank": 31,
      "team": "Saint Mary's",
      "rating": 1.497
    },
    {
      "rank": 32,
      "lastRank": 32,
      "team": "San Diego State",
      "rating": 1.464
    },
    {
      "rank": 33,
      "lastRank": 33,
      "team": "Ohio State",
      "rating": 1.413
    },
    {
      "rank": 34,
      "lastRank": 34,
      "team": "SMU",
      "rating": 1.387
    },
    {
      "rank": 35,
      "lastRank": 35,
      "team": "North Carolina",
      "rating": 1.384
    },
    {
      "rank": 36,
      "lastRank": 36,
      "team": "Baylor",
      "rating": 1.353
    },
    {
      "rank": 37,
      "lastRank": 37,
      "team": "Texas A&M",
      "rating": 1.352
    },
    {
      "rank": 38,
      "lastRank": 38,
      "team": "Saint Louis",
      "rating": 1.348
    },
    {
      "rank": 39,
      "lastRank": 39,
      "team": "Indiana",
      "rating": 1.317
    },
    {
      "rank": 40,
      "lastRank": 40,
      "team": "Virginia",
      "rating": 1.314
    },
    {
      "rank": 41,
      "lastRank": 41,
      "team": "Cincinnati",
      "rating": 1.313
    },
    {
      "rank": 42,
      "lastRank": 42,
      "team": "NC State",
      "rating": 1.287
    },
    {
      "rank": 43,
      "lastRank": 43,
      "team": "UCF",
      "rating": 1.284
    },
    {
      "rank": 44,
      "lastRank": 44,
      "team": "Villanova",
      "rating": 1.232
    },
    {
      "rank": 45,
      "lastRank": 45,
      "team": "New Mexico",
      "rating": 1.202
    },
    {
      "rank": 46,
      "lastRank": 46,
      "team": "TCU",
      "rating": 1.19
    },
    {
      "rank": 47,
      "lastRank": 47,
      "team": "Oklahoma",
      "rating": 1.185
    },
    {
      "rank": 48,
      "lastRank": 48,
      "team": "Washington",
      "rating": 1.182
    },
    {
      "rank": 49,
      "lastRank": 49,
      "team": "LSU",
      "rating": 1.181
    },
    {
      "rank": 50,
      "lastRank": 50,
      "team": "Missouri",
      "rating": 1.162
    },
    {
      "rank": 51,
      "lastRank": 51,
      "team": "Arizona State",
      "rating": 1.152
    },
    {
      "rank": 52,
      "lastRank": 52,
      "team": "Boise State",
      "rating": 1.115
    },
    {
      "rank": 53,
      "lastRank": 53,
      "team": "Miami",
      "rating": 1.112
    },
    {
      "rank": 54,
      "lastRank": 54,
      "team": "Stanford",
      "rating": 1.106
    },
    {
      "rank": 55,
      "lastRank": 55,
      "team": "South Florida",
      "rating": 1.039
    },
    {
      "rank": 56,
      "lastRank": 56,
      "team": "Clemson",
      "rating": 1.034
    },
    {
      "rank": 57,
      "lastRank": 57,
      "team": "Wake Forest",
      "rating": 1.004
    },
    {
      "rank": 58,
      "lastRank": 58,
      "team": "Akron",
      "rating": 0.998
    },
    {
      "rank": 59,
      "lastRank": 59,
      "team": "Oklahoma State",
      "rating": 0.994
    },
    {
      "rank": 60,
      "lastRank": 60,
      "team": "High Point",
      "rating": 0.984
    },
    {
      "rank": 61,
      "lastRank": 61,
      "team": "Southern California",
      "rating": 0.973
    },
    {
      "rank": 62,
      "lastRank": 62,
      "team": "Northwestern",
      "rating": 0.955
    },
    {
      "rank": 63,
      "lastRank": 63,
      "team": "VCU",
      "rating": 0.944
    },
    {
      "rank": 64,
      "lastRank": 64,
      "team": "Nevada",
      "rating": 0.939
    },
    {
      "rank": 65,
      "lastRank": 65,
      "team": "Colorado",
      "rating": 0.918
    },
    {
      "rank": 66,
      "lastRank": 66,
      "team": "California",
      "rating": 0.916
    },
    {
      "rank": 67,
      "lastRank": 67,
      "team": "Sam Houston",
      "rating": 0.912
    },
    {
      "rank": 68,
      "lastRank": 68,
      "team": "Belmont",
      "rating": 0.911
    },
    {
      "rank": 69,
      "lastRank": 69,
      "team": "Seton Hall",
      "rating": 0.907
    },
    {
      "rank": 70,
      "lastRank": 70,
      "team": "Oregon",
      "rating": 0.889
    },
    {
      "rank": 71,
      "lastRank": 71,
      "team": "Ole Miss",
      "rating": 0.877
    },
    {
      "rank": 72,
      "lastRank": 72,
      "team": "Grand Canyon",
      "rating": 0.842
    },
    {
      "rank": 73,
      "lastRank": 73,
      "team": "West Virginia",
      "rating": 0.835
    },
    {
      "rank": 74,
      "lastRank": 74,
      "team": "George Washington",
      "rating": 0.819
    },
    {
      "rank": 75,
      "lastRank": 75,
      "team": "Kansas State",
      "rating": 0.808
    },
    {
      "rank": 76,
      "lastRank": 76,
      "team": "Colorado State",
      "rating": 0.801
    },
    {
      "rank": 77,
      "lastRank": 77,
      "team": "Northern Iowa",
      "rating": 0.78
    },
    {
      "rank": 78,
      "lastRank": 78,
      "team": "Miami (OH)",
      "rating": 0.761
    },
    {
      "rank": 79,
      "lastRank": 79,
      "team": "Notre Dame",
      "rating": 0.755
    },
    {
      "rank": 80,
      "lastRank": 80,
      "team": "Virginia Tech",
      "rating": 0.737
    },
    {
      "rank": 81,
      "lastRank": 81,
      "team": "UNLV",
      "rating": 0.734
    },
    {
      "rank": 82,
      "lastRank": 82,
      "team": "Florida State",
      "rating": 0.7
    },
    {
      "rank": 83,
      "lastRank": 83,
      "team": "Utah Valley",
      "rating": 0.697
    },
    {
      "rank": 84,
      "lastRank": 84,
      "team": "Minnesota",
      "rating": 0.697
    },
    {
      "rank": 85,
      "lastRank": 85,
      "team": "Middle Tennessee",
      "rating": 0.693
    },
    {
      "rank": 86,
      "lastRank": 86,
      "team": "Wichita State",
      "rating": 0.69
    },
    {
      "rank": 87,
      "lastRank": 87,
      "team": "Butler",
      "rating": 0.682
    },
    {
      "rank": 88,
      "lastRank": 88,
      "team": "Providence",
      "rating": 0.682
    },
    {
      "rank": 89,
      "lastRank": 89,
      "team": "McNeese",
      "rating": 0.667
    },
    {
      "rank": 90,
      "lastRank": 90,
      "team": "Utah",
      "rating": 0.661
    },
    {
      "rank": 91,
      "lastRank": 91,
      "team": "Yale",
      "rating": 0.66
    },
    {
      "rank": 92,
      "lastRank": 92,
      "team": "Kennesaw State",
      "rating": 0.658
    },
    {
      "rank": 93,
      "lastRank": 93,
      "team": "Creighton",
      "rating": 0.655
    },
    {
      "rank": 94,
      "lastRank": 94,
      "team": "Dayton",
      "rating": 0.654
    },
    {
      "rank": 95,
      "lastRank": 95,
      "team": "Western Kentucky",
      "rating": 0.649
    },
    {
      "rank": 96,
      "lastRank": 96,
      "team": "Liberty",
      "rating": 0.591
    },
    {
      "rank": 97,
      "lastRank": 97,
      "team": "Xavier",
      "rating": 0.59
    },
    {
      "rank": 98,
      "lastRank": 98,
      "team": "Seattle",
      "rating": 0.587
    },
    {
      "rank": 99,
      "lastRank": 99,
      "team": "Mississippi State",
      "rating": 0.577
    },
    {
      "rank": 100,
      "lastRank": 100,
      "team": "Illinois State",
      "rating": 0.568
    },
    {
      "rank": 101,
      "lastRank": 101,
      "team": "South Carolina",
      "rating": 0.563
    },
    {
      "rank": 102,
      "lastRank": 102,
      "team": "Syracuse",
      "rating": 0.543
    },
    {
      "rank": 103,
      "lastRank": 103,
      "team": "Murray State",
      "rating": 0.536
    },
    {
      "rank": 104,
      "lastRank": 104,
      "team": "Washington State",
      "rating": 0.535
    },
    {
      "rank": 105,
      "lastRank": 105,
      "team": "Davidson",
      "rating": 0.534
    },
    {
      "rank": 106,
      "lastRank": 106,
      "team": "Bradley",
      "rating": 0.511
    },
    {
      "rank": 107,
      "lastRank": 107,
      "team": "Tulsa",
      "rating": 0.493
    },
    {
      "rank": 108,
      "lastRank": 108,
      "team": "Memphis",
      "rating": 0.481
    },
    {
      "rank": 109,
      "lastRank": 109,
      "team": "Montana State",
      "rating": 0.478
    },
    {
      "rank": 110,
      "lastRank": 110,
      "team": "Winthrop",
      "rating": 0.475
    },
    {
      "rank": 111,
      "lastRank": 111,
      "team": "UT Rio Grande Valley",
      "rating": 0.474
    },
    {
      "rank": 112,
      "lastRank": 112,
      "team": "Bowling Green",
      "rating": 0.47
    },
    {
      "rank": 113,
      "lastRank": 113,
      "team": "New Mexico State",
      "rating": 0.468
    },
    {
      "rank": 114,
      "lastRank": 114,
      "team": "San Francisco",
      "rating": 0.459
    },
    {
      "rank": 115,
      "lastRank": 115,
      "team": "Marquette",
      "rating": 0.456
    },
    {
      "rank": 116,
      "lastRank": 116,
      "team": "UC Irvine",
      "rating": 0.453
    },
    {
      "rank": 117,
      "lastRank": 117,
      "team": "Duquesne",
      "rating": 0.444
    },
    {
      "rank": 118,
      "lastRank": 118,
      "team": "Pittsburgh",
      "rating": 0.443
    },
    {
      "rank": 119,
      "lastRank": 119,
      "team": "DePaul",
      "rating": 0.432
    },
    {
      "rank": 120,
      "lastRank": 120,
      "team": "Jacksonville State",
      "rating": 0.431
    },
    {
      "rank": 121,
      "lastRank": 121,
      "team": "Southern Illinois",
      "rating": 0.428
    },
    {
      "rank": 122,
      "lastRank": 122,
      "team": "Florida Atlantic",
      "rating": 0.417
    },
    {
      "rank": 123,
      "lastRank": 123,
      "team": "Georgetown",
      "rating": 0.406
    },
    {
      "rank": 124,
      "lastRank": 124,
      "team": "Maryland",
      "rating": 0.401
    },
    {
      "rank": 125,
      "lastRank": 125,
      "team": "UIC",
      "rating": 0.399
    },
    {
      "rank": 126,
      "lastRank": 126,
      "team": "Kent State",
      "rating": 0.385
    },
    {
      "rank": 127,
      "lastRank": 127,
      "team": "Fresno State",
      "rating": 0.38
    },
    {
      "rank": 128,
      "lastRank": 128,
      "team": "Stephen F. Austin",
      "rating": 0.37
    },
    {
      "rank": 129,
      "lastRank": 129,
      "team": "Wyoming",
      "rating": 0.369
    },
    {
      "rank": 130,
      "lastRank": 130,
      "team": "Pacific",
      "rating": 0.361
    },
    {
      "rank": 131,
      "lastRank": 131,
      "team": "Penn State",
      "rating": 0.347
    },
    {
      "rank": 132,
      "lastRank": 132,
      "team": "California Baptist",
      "rating": 0.322
    },
    {
      "rank": 133,
      "lastRank": 133,
      "team": "Portland State",
      "rating": 0.31
    },
    {
      "rank": 134,
      "lastRank": 134,
      "team": "Northern Colorado",
      "rating": 0.305
    },
    {
      "rank": 135,
      "lastRank": 135,
      "team": "St. Thomas - Minnesota",
      "rating": 0.301
    },
    {
      "rank": 136,
      "lastRank": 136,
      "team": "St. Bonaventure",
      "rating": 0.301
    },
    {
      "rank": 137,
      "lastRank": 137,
      "team": "Toledo",
      "rating": 0.3
    },
    {
      "rank": 138,
      "lastRank": 138,
      "team": "North Dakota State",
      "rating": 0.294
    },
    {
      "rank": 139,
      "lastRank": 139,
      "team": "Idaho",
      "rating": 0.291
    },
    {
      "rank": 140,
      "lastRank": 140,
      "team": "UNC Wilmington",
      "rating": 0.286
    },
    {
      "rank": 141,
      "lastRank": 141,
      "team": "North Texas",
      "rating": 0.284
    },
    {
      "rank": 142,
      "lastRank": 142,
      "team": "Florida International",
      "rating": 0.28
    },
    {
      "rank": 143,
      "lastRank": 143,
      "team": "George Mason",
      "rating": 0.276
    },
    {
      "rank": 144,
      "lastRank": 144,
      "team": "Missouri State",
      "rating": 0.275
    },
    {
      "rank": 145,
      "lastRank": 145,
      "team": "Abilene Christian",
      "rating": 0.27
    },
    {
      "rank": 146,
      "lastRank": 146,
      "team": "UT Arlington",
      "rating": 0.268
    },
    {
      "rank": 147,
      "lastRank": 147,
      "team": "Loyola Marymount",
      "rating": 0.266
    },
    {
      "rank": 148,
      "lastRank": 148,
      "team": "Tarleton",
      "rating": 0.256
    },
    {
      "rank": 149,
      "lastRank": 149,
      "team": "Richmond",
      "rating": 0.243
    },
    {
      "rank": 150,
      "lastRank": 150,
      "team": "East Tennessee State",
      "rating": 0.242
    },
    {
      "rank": 151,
      "lastRank": 151,
      "team": "UC Santa Barbara",
      "rating": 0.236
    },
    {
      "rank": 152,
      "lastRank": 152,
      "team": "Cornell",
      "rating": 0.233
    },
    {
      "rank": 153,
      "lastRank": 153,
      "team": "Rutgers",
      "rating": 0.221
    },
    {
      "rank": 154,
      "lastRank": 154,
      "team": "Hawaii",
      "rating": 0.22
    },
    {
      "rank": 155,
      "lastRank": 155,
      "team": "William & Mary",
      "rating": 0.209
    },
    {
      "rank": 156,
      "lastRank": 156,
      "team": "UC San Diego",
      "rating": 0.202
    },
    {
      "rank": 157,
      "lastRank": 157,
      "team": "Weber State",
      "rating": 0.183
    },
    {
      "rank": 158,
      "lastRank": 158,
      "team": "Texas A&M-CC",
      "rating": 0.179
    },
    {
      "rank": 159,
      "lastRank": 159,
      "team": "Rhode Island",
      "rating": 0.172
    },
    {
      "rank": 160,
      "lastRank": 160,
      "team": "Wright State",
      "rating": 0.171
    },
    {
      "rank": 161,
      "lastRank": 161,
      "team": "Montana",
      "rating": 0.165
    },
    {
      "rank": 162,
      "lastRank": 162,
      "team": "UAB",
      "rating": 0.145
    },
    {
      "rank": 163,
      "lastRank": 163,
      "team": "Mercer",
      "rating": 0.117
    },
    {
      "rank": 164,
      "lastRank": 164,
      "team": "UMass",
      "rating": 0.103
    },
    {
      "rank": 165,
      "lastRank": 165,
      "team": "San Diego",
      "rating": 0.1
    },
    {
      "rank": 166,
      "lastRank": 166,
      "team": "Oregon State",
      "rating": 0.097
    },
    {
      "rank": 167,
      "lastRank": 167,
      "team": "Louisiana Tech",
      "rating": 0.089
    },
    {
      "rank": 168,
      "lastRank": 168,
      "team": "Eastern Washington",
      "rating": 0.083
    },
    {
      "rank": 169,
      "lastRank": 169,
      "team": "Utah Tech",
      "rating": 0.082
    },
    {
      "rank": 170,
      "lastRank": 170,
      "team": "Columbia",
      "rating": 0.066
    },
    {
      "rank": 171,
      "lastRank": 171,
      "team": "Drake",
      "rating": 0.062
    },
    {
      "rank": 172,
      "lastRank": 172,
      "team": "Portland",
      "rating": 0.049
    },
    {
      "rank": 173,
      "lastRank": 173,
      "team": "CSU Fullerton",
      "rating": 0.043
    },
    {
      "rank": 174,
      "lastRank": 174,
      "team": "Austin Peay",
      "rating": 0.035
    },
    {
      "rank": 175,
      "lastRank": 175,
      "team": "UTEP",
      "rating": 0.032
    },
    {
      "rank": 176,
      "lastRank": 176,
      "team": "Idaho State",
      "rating": 0.026
    },
    {
      "rank": 177,
      "lastRank": 177,
      "team": "Northern Kentucky",
      "rating": 0.019
    },
    {
      "rank": 178,
      "lastRank": 178,
      "team": "San Jose State",
      "rating": 0.016
    },
    {
      "rank": 179,
      "lastRank": 179,
      "team": "Troy",
      "rating": 0.016
    },
    {
      "rank": 180,
      "lastRank": 180,
      "team": "Campbell",
      "rating": 0.003
    },
    {
      "rank": 181,
      "lastRank": 181,
      "team": "Oakland",
      "rating": -0.009
    },
    {
      "rank": 182,
      "lastRank": 182,
      "team": "Hofstra",
      "rating": -0.012
    },
    {
      "rank": 183,
      "lastRank": 183,
      "team": "CSU Northridge",
      "rating": -0.022
    },
    {
      "rank": 184,
      "lastRank": 184,
      "team": "Robert Morris",
      "rating": -0.025
    },
    {
      "rank": 185,
      "lastRank": 185,
      "team": "Valparaiso",
      "rating": -0.03
    },
    {
      "rank": 186,
      "lastRank": 186,
      "team": "Tennessee State",
      "rating": -0.035
    },
    {
      "rank": 187,
      "lastRank": 187,
      "team": "Arkansas State",
      "rating": -0.045
    },
    {
      "rank": 188,
      "lastRank": 188,
      "team": "Temple",
      "rating": -0.05
    },
    {
      "rank": 189,
      "lastRank": 189,
      "team": "Western Carolina",
      "rating": -0.054
    },
    {
      "rank": 190,
      "lastRank": 190,
      "team": "UC Davis",
      "rating": -0.055
    },
    {
      "rank": 191,
      "lastRank": 191,
      "team": "South Dakota State",
      "rating": -0.057
    },
    {
      "rank": 192,
      "lastRank": 192,
      "team": "Boston College",
      "rating": -0.063
    },
    {
      "rank": 193,
      "lastRank": 193,
      "team": "Fordham",
      "rating": -0.07
    },
    {
      "rank": 194,
      "lastRank": 194,
      "team": "Ohio",
      "rating": -0.082
    },
    {
      "rank": 195,
      "lastRank": 195,
      "team": "Sacramento State",
      "rating": -0.093
    },
    {
      "rank": 196,
      "lastRank": 196,
      "team": "St. Joseph's",
      "rating": -0.1
    },
    {
      "rank": 197,
      "lastRank": 197,
      "team": "Central Arkansas",
      "rating": -0.104
    },
    {
      "rank": 198,
      "lastRank": 198,
      "team": "Lamar",
      "rating": -0.12
    },
    {
      "rank": 199,
      "lastRank": 199,
      "team": "Radford",
      "rating": -0.121
    },
    {
      "rank": 200,
      "lastRank": 200,
      "team": "Incarnate Word",
      "rating": -0.122
    },
    {
      "rank": 201,
      "lastRank": 201,
      "team": "Southern Utah",
      "rating": -0.125
    },
    {
      "rank": 202,
      "lastRank": 202,
      "team": "Rice",
      "rating": -0.132
    },
    {
      "rank": 203,
      "lastRank": 203,
      "team": "Youngstown State",
      "rating": -0.14
    },
    {
      "rank": 204,
      "lastRank": 204,
      "team": "Lipscomb",
      "rating": -0.149
    },
    {
      "rank": 205,
      "lastRank": 205,
      "team": "Southeast Missouri State",
      "rating": -0.16
    },
    {
      "rank": 206,
      "lastRank": 206,
      "team": "Furman",
      "rating": -0.161
    },
    {
      "rank": 207,
      "lastRank": 207,
      "team": "Charlotte",
      "rating": -0.193
    },
    {
      "rank": 208,
      "lastRank": 208,
      "team": "Charleston",
      "rating": -0.194
    },
    {
      "rank": 209,
      "lastRank": 209,
      "team": "Marshall",
      "rating": -0.204
    },
    {
      "rank": 210,
      "lastRank": 210,
      "team": "Pepperdine",
      "rating": -0.206
    },
    {
      "rank": 211,
      "lastRank": 211,
      "team": "Buffalo",
      "rating": -0.207
    },
    {
      "rank": 212,
      "lastRank": 212,
      "team": "Samford",
      "rating": -0.213
    },
    {
      "rank": 213,
      "lastRank": 213,
      "team": "Indiana State",
      "rating": -0.214
    },
    {
      "rank": 214,
      "lastRank": 214,
      "team": "Nicholls",
      "rating": -0.217
    },
    {
      "rank": 215,
      "lastRank": 215,
      "team": "New Orleans",
      "rating": -0.22
    },
    {
      "rank": 216,
      "lastRank": 216,
      "team": "Northern Arizona",
      "rating": -0.222
    },
    {
      "rank": 217,
      "lastRank": 217,
      "team": "UNC Asheville",
      "rating": -0.225
    },
    {
      "rank": 218,
      "lastRank": 218,
      "team": "Denver",
      "rating": -0.226
    },
    {
      "rank": 219,
      "lastRank": 219,
      "team": "Detroit",
      "rating": -0.232
    },
    {
      "rank": 220,
      "lastRank": 220,
      "team": "Cal Poly",
      "rating": -0.241
    },
    {
      "rank": 221,
      "lastRank": 221,
      "team": "Pennsylvania",
      "rating": -0.242
    },
    {
      "rank": 222,
      "lastRank": 222,
      "team": "Purdue Fort Wayne",
      "rating": -0.245
    },
    {
      "rank": 223,
      "lastRank": 223,
      "team": "Elon",
      "rating": -0.252
    },
    {
      "rank": 224,
      "lastRank": 224,
      "team": "Georgia Tech",
      "rating": -0.259
    },
    {
      "rank": 225,
      "lastRank": 225,
      "team": "UT Martin",
      "rating": -0.268
    },
    {
      "rank": 226,
      "lastRank": 226,
      "team": "La Salle",
      "rating": -0.298
    },
    {
      "rank": 227,
      "lastRank": 227,
      "team": "Long Beach State",
      "rating": -0.299
    },
    {
      "rank": 228,
      "lastRank": 228,
      "team": "Eastern Michigan",
      "rating": -0.308
    },
    {
      "rank": 229,
      "lastRank": 229,
      "team": "Wofford",
      "rating": -0.331
    },
    {
      "rank": 230,
      "lastRank": 230,
      "team": "North Dakota",
      "rating": -0.352
    },
    {
      "rank": 231,
      "lastRank": 231,
      "team": "Green Bay",
      "rating": -0.363
    },
    {
      "rank": 232,
      "lastRank": 232,
      "team": "Omaha",
      "rating": -0.366
    },
    {
      "rank": 233,
      "lastRank": 233,
      "team": "Chattanooga",
      "rating": -0.367
    },
    {
      "rank": 234,
      "lastRank": 234,
      "team": "Evansville",
      "rating": -0.369
    },
    {
      "rank": 235,
      "lastRank": 235,
      "team": "Queens University",
      "rating": -0.369
    },
    {
      "rank": 236,
      "lastRank": 236,
      "team": "Brown",
      "rating": -0.375
    },
    {
      "rank": 237,
      "lastRank": 237,
      "team": "Towson",
      "rating": -0.38
    },
    {
      "rank": 238,
      "lastRank": 238,
      "team": "Tulane",
      "rating": -0.382
    },
    {
      "rank": 239,
      "lastRank": 239,
      "team": "Lindenwood",
      "rating": -0.403
    },
    {
      "rank": 240,
      "lastRank": 240,
      "team": "Milwaukee",
      "rating": -0.408
    },
    {
      "rank": 241,
      "lastRank": 241,
      "team": "Monmouth",
      "rating": -0.427
    },
    {
      "rank": 242,
      "lastRank": 242,
      "team": "Dartmouth",
      "rating": -0.431
    },
    {
      "rank": 243,
      "lastRank": 243,
      "team": "Charleston Southern",
      "rating": -0.443
    },
    {
      "rank": 244,
      "lastRank": 244,
      "team": "Central Michigan",
      "rating": -0.456
    },
    {
      "rank": 245,
      "lastRank": 245,
      "team": "Harvard",
      "rating": -0.464
    },
    {
      "rank": 246,
      "lastRank": 246,
      "team": "Appalachian State",
      "rating": -0.466
    },
    {
      "rank": 247,
      "lastRank": 247,
      "team": "South Alabama",
      "rating": -0.475
    },
    {
      "rank": 248,
      "lastRank": 248,
      "team": "South Carolina Upstate",
      "rating": -0.482
    },
    {
      "rank": 249,
      "lastRank": 249,
      "team": "Stony Brook",
      "rating": -0.483
    },
    {
      "rank": 250,
      "lastRank": 250,
      "team": "UC Riverside",
      "rating": -0.486
    },
    {
      "rank": 251,
      "lastRank": 251,
      "team": "Presbyterian",
      "rating": -0.493
    },
    {
      "rank": 252,
      "lastRank": 252,
      "team": "Western Michigan",
      "rating": -0.494
    },
    {
      "rank": 253,
      "lastRank": 253,
      "team": "Florida Gulf Coast",
      "rating": -0.498
    },
    {
      "rank": 254,
      "lastRank": 254,
      "team": "Morehead State",
      "rating": -0.499
    },
    {
      "rank": 255,
      "lastRank": 255,
      "team": "Oral Roberts",
      "rating": -0.52
    },
    {
      "rank": 256,
      "lastRank": 256,
      "team": "UNC Greensboro",
      "rating": -0.53
    },
    {
      "rank": 257,
      "lastRank": 257,
      "team": "Longwood",
      "rating": -0.535
    },
    {
      "rank": 258,
      "lastRank": 258,
      "team": "Eastern Kentucky",
      "rating": -0.552
    },
    {
      "rank": 259,
      "lastRank": 259,
      "team": "SIU Edwardsville",
      "rating": -0.556
    },
    {
      "rank": 260,
      "lastRank": 260,
      "team": "James Madison",
      "rating": -0.561
    },
    {
      "rank": 261,
      "lastRank": 261,
      "team": "Bellarmine",
      "rating": -0.562
    },
    {
      "rank": 262,
      "lastRank": 262,
      "team": "East Texas A&M",
      "rating": -0.576
    },
    {
      "rank": 263,
      "lastRank": 263,
      "team": "Northwestern State",
      "rating": -0.579
    },
    {
      "rank": 264,
      "lastRank": 264,
      "team": "Hampton",
      "rating": -0.591
    },
    {
      "rank": 265,
      "lastRank": 265,
      "team": "East Carolina",
      "rating": -0.601
    },
    {
      "rank": 266,
      "lastRank": 266,
      "team": "South Dakota",
      "rating": -0.603
    },
    {
      "rank": 267,
      "lastRank": 267,
      "team": "IU Indianapolis",
      "rating": -0.62
    },
    {
      "rank": 268,
      "lastRank": 268,
      "team": "Princeton",
      "rating": -0.625
    },
    {
      "rank": 269,
      "lastRank": 269,
      "team": "Drexel",
      "rating": -0.625
    },
    {
      "rank": 270,
      "lastRank": 270,
      "team": "Georgia Southern",
      "rating": -0.625
    },
    {
      "rank": 271,
      "lastRank": 271,
      "team": "Ball State",
      "rating": -0.63
    },
    {
      "rank": 272,
      "lastRank": 272,
      "team": "Old Dominion",
      "rating": -0.643
    },
    {
      "rank": 273,
      "lastRank": 273,
      "team": "Southern Miss",
      "rating": -0.645
    },
    {
      "rank": 274,
      "lastRank": 274,
      "team": "Texas State",
      "rating": -0.648
    },
    {
      "rank": 275,
      "lastRank": 275,
      "team": "Long Island University",
      "rating": -0.67
    },
    {
      "rank": 276,
      "lastRank": 276,
      "team": "North Carolina A&T",
      "rating": -0.679
    },
    {
      "rank": 277,
      "lastRank": 277,
      "team": "Loyola Chicago",
      "rating": -0.682
    },
    {
      "rank": 278,
      "lastRank": 278,
      "team": "Navy",
      "rating": -0.684
    },
    {
      "rank": 279,
      "lastRank": 279,
      "team": "Delaware",
      "rating": -0.684
    },
    {
      "rank": 280,
      "lastRank": 280,
      "team": "Houston Christian",
      "rating": -0.691
    },
    {
      "rank": 281,
      "lastRank": 281,
      "team": "Eastern Illinois",
      "rating": -0.699
    },
    {
      "rank": 282,
      "lastRank": 282,
      "team": "Coastal Carolina",
      "rating": -0.705
    },
    {
      "rank": 283,
      "lastRank": 283,
      "team": "Jacksonville",
      "rating": -0.735
    },
    {
      "rank": 284,
      "lastRank": 284,
      "team": "Tennessee Tech",
      "rating": -0.738
    },
    {
      "rank": 285,
      "lastRank": 285,
      "team": "Northern Illinois",
      "rating": -0.739
    },
    {
      "rank": 286,
      "lastRank": 286,
      "team": "Colgate",
      "rating": -0.74
    },
    {
      "rank": 287,
      "lastRank": 287,
      "team": "American University",
      "rating": -0.745
    },
    {
      "rank": 288,
      "lastRank": 288,
      "team": "Little Rock",
      "rating": -0.745
    },
    {
      "rank": 289,
      "lastRank": 289,
      "team": "Cleveland State",
      "rating": -0.752
    },
    {
      "rank": 290,
      "lastRank": 290,
      "team": "Southern",
      "rating": -0.791
    },
    {
      "rank": 291,
      "lastRank": 291,
      "team": "CSU Bakersfield",
      "rating": -0.814
    },
    {
      "rank": 292,
      "lastRank": 292,
      "team": "SE Louisiana",
      "rating": -0.818
    },
    {
      "rank": 293,
      "lastRank": 293,
      "team": "Howard",
      "rating": -0.841
    },
    {
      "rank": 294,
      "lastRank": 294,
      "team": "Northeastern",
      "rating": -0.851
    },
    {
      "rank": 295,
      "lastRank": 295,
      "team": "The Citadel",
      "rating": -0.927
    },
    {
      "rank": 296,
      "lastRank": 296,
      "team": "West Georgia",
      "rating": -0.933
    },
    {
      "rank": 297,
      "lastRank": 297,
      "team": "Air Force",
      "rating": -0.944
    },
    {
      "rank": 298,
      "lastRank": 298,
      "team": "UTSA",
      "rating": -0.959
    },
    {
      "rank": 299,
      "lastRank": 299,
      "team": "Le Moyne",
      "rating": -0.965
    },
    {
      "rank": 300,
      "lastRank": 300,
      "team": "Vermont",
      "rating": -0.979
    },
    {
      "rank": 301,
      "lastRank": 301,
      "team": "Albany",
      "rating": -0.991
    },
    {
      "rank": 302,
      "lastRank": 302,
      "team": "Norfolk State",
      "rating": -1.036
    },
    {
      "rank": 303,
      "lastRank": 303,
      "team": "Georgia State",
      "rating": -1.046
    },
    {
      "rank": 304,
      "lastRank": 304,
      "team": "Mercyhurst",
      "rating": -1.049
    },
    {
      "rank": 305,
      "lastRank": 305,
      "team": "UMBC",
      "rating": -1.051
    },
    {
      "rank": 306,
      "lastRank": 306,
      "team": "Louisiana",
      "rating": -1.053
    },
    {
      "rank": 307,
      "lastRank": 307,
      "team": "North Florida",
      "rating": -1.109
    },
    {
      "rank": 308,
      "lastRank": 308,
      "team": "Marist",
      "rating": -1.143
    },
    {
      "rank": 309,
      "lastRank": 309,
      "team": "VMI",
      "rating": -1.146
    },
    {
      "rank": 310,
      "lastRank": 310,
      "team": "Boston University",
      "rating": -1.16
    },
    {
      "rank": 311,
      "lastRank": 311,
      "team": "Stetson",
      "rating": -1.161
    },
    {
      "rank": 312,
      "lastRank": 312,
      "team": "Saint Peter's",
      "rating": -1.168
    },
    {
      "rank": 313,
      "lastRank": 313,
      "team": "Kansas City",
      "rating": -1.174
    },
    {
      "rank": 314,
      "lastRank": 314,
      "team": "Southern Indiana",
      "rating": -1.184
    },
    {
      "rank": 315,
      "lastRank": 315,
      "team": "UMass Lowell",
      "rating": -1.209
    },
    {
      "rank": 316,
      "lastRank": 316,
      "team": "Siena",
      "rating": -1.214
    },
    {
      "rank": 317,
      "lastRank": 317,
      "team": "Quinnipiac",
      "rating": -1.216
    },
    {
      "rank": 318,
      "lastRank": 318,
      "team": "Lehigh Mountain",
      "rating": -1.235
    },
    {
      "rank": 319,
      "lastRank": 319,
      "team": "Prairie View A&M",
      "rating": -1.235
    },
    {
      "rank": 320,
      "lastRank": 320,
      "team": "Central Connecticut",
      "rating": -1.252
    },
    {
      "rank": 321,
      "lastRank": 321,
      "team": "Merrimack",
      "rating": -1.258
    },
    {
      "rank": 322,
      "lastRank": 322,
      "team": "North Carolina Central",
      "rating": -1.277
    },
    {
      "rank": 323,
      "lastRank": 323,
      "team": "North Alabama",
      "rating": -1.277
    },
    {
      "rank": 324,
      "lastRank": 324,
      "team": "Wagner",
      "rating": -1.299
    },
    {
      "rank": 325,
      "lastRank": 325,
      "team": "Iona",
      "rating": -1.302
    },
    {
      "rank": 326,
      "lastRank": 326,
      "team": "Loyola (MD)",
      "rating": -1.313
    },
    {
      "rank": 327,
      "lastRank": 327,
      "team": "Bethune-Cookman",
      "rating": -1.32
    },
    {
      "rank": 328,
      "lastRank": 328,
      "team": "Fairfield",
      "rating": -1.333
    },
    {
      "rank": 329,
      "lastRank": 329,
      "team": "Fairleigh Dickinson",
      "rating": -1.365
    },
    {
      "rank": 330,
      "lastRank": 330,
      "team": "Grambling",
      "rating": -1.39
    },
    {
      "rank": 331,
      "lastRank": 331,
      "team": "Gardner-Webb",
      "rating": -1.4
    },
    {
      "rank": 332,
      "lastRank": 332,
      "team": "Texas Southern",
      "rating": -1.404
    },
    {
      "rank": 333,
      "lastRank": 333,
      "team": "Western Illinois",
      "rating": -1.407
    },
    {
      "rank": 334,
      "lastRank": 334,
      "team": "New Haven",
      "rating": -1.413
    },
    {
      "rank": 335,
      "lastRank": 335,
      "team": "Morgan State",
      "rating": -1.417
    },
    {
      "rank": 336,
      "lastRank": 336,
      "team": "Alabama State",
      "rating": -1.421
    },
    {
      "rank": 337,
      "lastRank": 337,
      "team": "Chicago State",
      "rating": -1.432
    },
    {
      "rank": 338,
      "lastRank": 338,
      "team": "NJIT",
      "rating": -1.446
    },
    {
      "rank": 339,
      "lastRank": 339,
      "team": "Alabama A&M",
      "rating": -1.463
    },
    {
      "rank": 340,
      "lastRank": 340,
      "team": "Arkansas-Pine Bluff",
      "rating": -1.475
    },
    {
      "rank": 341,
      "lastRank": 341,
      "team": "Mount St. Mary's",
      "rating": -1.475
    },
    {
      "rank": 342,
      "lastRank": 342,
      "team": "Army",
      "rating": -1.504
    },
    {
      "rank": 343,
      "lastRank": 343,
      "team": "Lafayette",
      "rating": -1.504
    },
    {
      "rank": 344,
      "lastRank": 344,
      "team": "St. Francis (PA)",
      "rating": -1.512
    },
    {
      "rank": 345,
      "lastRank": 345,
      "team": "New Hampshire",
      "rating": -1.524
    },
    {
      "rank": 346,
      "lastRank": 346,
      "team": "Bucknell",
      "rating": -1.555
    },
    {
      "rank": 347,
      "lastRank": 347,
      "team": "Holy Cross",
      "rating": -1.594
    },
    {
      "rank": 348,
      "lastRank": 348,
      "team": "Stonehill",
      "rating": -1.627
    },
    {
      "rank": 349,
      "lastRank": 349,
      "team": "Florida A&M",
      "rating": -1.629
    },
    {
      "rank": 350,
      "lastRank": 350,
      "team": "Maryland-Eastern Shore",
      "rating": -1.635
    },
    {
      "rank": 351,
      "lastRank": 351,
      "team": "Bryant",
      "rating": -1.691
    },
    {
      "rank": 352,
      "lastRank": 352,
      "team": "South Carolina State",
      "rating": -1.708
    },
    {
      "rank": 353,
      "lastRank": 353,
      "team": "Sacred Heart",
      "rating": -1.718
    },
    {
      "rank": 354,
      "lastRank": 354,
      "team": "Maine",
      "rating": -1.776
    },
    {
      "rank": 355,
      "lastRank": 355,
      "team": "UL Monroe",
      "rating": -1.792
    },
    {
      "rank": 356,
      "lastRank": 356,
      "team": "Jackson State",
      "rating": -1.931
    },
    {
      "rank": 357,
      "lastRank": 357,
      "team": "Canisius",
      "rating": -1.932
    },
    {
      "rank": 358,
      "lastRank": 358,
      "team": "Niagara",
      "rating": -1.955
    },
    {
      "rank": 359,
      "lastRank": 359,
      "team": "Manhatten",
      "rating": -1.975
    },
    {
      "rank": 360,
      "lastRank": 360,
      "team": "Rider",
      "rating": -2.041
    },
    {
      "rank": 361,
      "lastRank": 361,
      "team": "Alcorn State",
      "rating": -2.133
    },
    {
      "rank": 362,
      "lastRank": 362,
      "team": "Delaware State",
      "rating": -2.201
    },
    {
      "rank": 363,
      "lastRank": 363,
      "team": "Coppin State",
      "rating": -2.201
    },
    {
      "rank": 364,
      "lastRank": 364,
      "team": "Binghamton",
      "rating": -2.204
    },
    {
      "rank": 365,
      "lastRank": 365,
      "team": "Mississippi Valley State",
      "rating": -2.535
    }
  ]
}